weighbridge_simulator/__init__.py
weighbridge_simulator/__main__.py
weighbridge_simulator-0.3.1.dist-info/LICENSE
weighbridge_simulator-0.3.1.dist-info/METADATA
weighbridge_simulator-0.3.1.dist-info/WHEEL
weighbridge_simulator-0.3.1.dist-info/entry_points.txt
weighbridge_simulator-0.3.1.dist-info/RECORD
