Metadata-Version: 2.1
Name: weighbridge-simulator
Version: 0.3.1
Summary: A command line tool continuously send data to a serial port to simulate weighbridge communicating.
Home-page: https://github.com/garrett-he/weighbridge-simulator
License: BSD-3-Clause
Keywords: weighbridge,simulator,serial-communication
Author: Garrett HE
Author-email: garrett.he@hotmail.com
Requires-Python: >=3.8,<3.13
Classifier: Development Status :: 3 - Alpha
Classifier: Environment :: Console
Classifier: Intended Audience :: Developers
Classifier: License :: OSI Approved :: BSD License
Classifier: Operating System :: OS Independent
Classifier: Programming Language :: Python :: 3
Classifier: Programming Language :: Python :: 3.8
Classifier: Programming Language :: Python :: 3.9
Classifier: Programming Language :: Python :: 3.10
Classifier: Programming Language :: Python :: 3.11
Classifier: Programming Language :: Python :: 3.12
Classifier: Topic :: Utilities
Requires-Dist: click (>=8.1.7,<9.0.0)
Requires-Dist: pyserial (>=3.5,<4.0)
Project-URL: Repository, https://github.com/garrett-he/weighbridge-simulator.git
